umbral_pre/__init__.py
umbral_pre/__init__.pyi
umbral_pre/_umbral.cpython-37m-darwin.so
umbral_pre/py.typed
umbral_pre-0.11.0.dist-info/LICENSE
umbral_pre-0.11.0.dist-info/METADATA
umbral_pre-0.11.0.dist-info/WHEEL
umbral_pre-0.11.0.dist-info/top_level.txt
umbral_pre-0.11.0.dist-info/RECORD
