Metadata-Version: 2.1
Name: umbral-pre
Version: 0.11.0
Summary: Implementation of Umbral proxy reencryption algorithm
Home-page: https://github.com/nucypher/rust-umbral/tree/master/umbral-pre-python
Author: Bogdan Opanchuk
Author-email: bogdan@opanchuk.net
Classifier: Development Status :: 3 - Alpha
Classifier: Intended Audience :: Science/Research
Classifier: License :: OSI Approved :: GNU General Public License v3 (GPLv3)
Classifier: Natural Language :: English
Classifier: Programming Language :: Rust
Classifier: Programming Language :: Python :: Implementation :: CPython
Classifier: Programming Language :: Python :: 3 :: Only
Classifier: Programming Language :: Python :: 3.7
Classifier: Programming Language :: Python :: 3.8
Classifier: Programming Language :: Python :: 3.9
Classifier: Programming Language :: Python :: 3.10
Classifier: Topic :: Security :: Cryptography
License-File: LICENSE
